ocrmypdf_appleocr/__init__.py
ocrmypdf_appleocr/common.py
ocrmypdf_appleocr/hocr.py
ocrmypdf_appleocr/livetext.py
ocrmypdf_appleocr/pdf.py
ocrmypdf_appleocr/pdf.ttf
ocrmypdf_appleocr/vision.py
ocrmypdf_appleocr-0.3.1.dist-info/licenses/LICENSE
ocrmypdf_appleocr-0.3.1.dist-info/METADATA
ocrmypdf_appleocr-0.3.1.dist-info/WHEEL
ocrmypdf_appleocr-0.3.1.dist-info/top_level.txt
ocrmypdf_appleocr-0.3.1.dist-info/RECORD
