Metadata-Version: 2.4
Name: ocrmypdf-appleocr
Version: 0.3.1
Summary: Plugin to run OCRmyPDF with Apple Vision Framework OCR engine
Author-email: Masahiro Kiyota <hiro@juzbox.com>
License-Expression: MIT
Project-URL: Homepage, https://github.com/mkyt/OCRmyPDF-AppleOCR
Project-URL: Repository, https://github.com/mkyt/OCRmyPDF-AppleOCR.git
Keywords: pdf,ocr,optical character recognition,apple,vision,ocrmypdf,plugin
Classifier: Development Status :: 4 - Beta
Classifier: Environment :: Plugins
Classifier: Intended Audience :: End Users/Desktop
Classifier: Intended Audience :: Science/Research
Classifier: Operating System :: MacOS :: MacOS X
Classifier: Programming Language :: Python :: 3 :: Only
Classifier: Topic :: Scientific/Engineering :: Image Recognition
Classifier: Topic :: Software Development :: Libraries
Classifier: Topic :: Text Processing :: Linguistic
Classifier: Topic :: Text Processing :: Markup
Classifier: Topic :: Utilities
Requires-Python: >=3.10
License-File: LICENSE
Requires-Dist: pyobjc-core
Requires-Dist: pyobjc-framework-Vision
Requires-Dist: pyobjc-framework-Cocoa
Requires-Dist: ocrmypdf>=14.2.1
Requires-Dist: Pillow>=10.0.1
Requires-Dist: pikepdf>=8.10.1
Dynamic: license-file
